flickr/__init__.py
flickr/__main__.py
flickr/constants.py
flickr/flickr_api.py
flickr/flickr_model.py
flickr/mirroring_agent.py
flickr/parser.py
python_flickr_mirroring-1.0.0.dist-info/LICENSE
python_flickr_mirroring-1.0.0.dist-info/METADATA
python_flickr_mirroring-1.0.0.dist-info/WHEEL
python_flickr_mirroring-1.0.0.dist-info/entry_points.txt
python_flickr_mirroring-1.0.0.dist-info/top_level.txt
python_flickr_mirroring-1.0.0.dist-info/RECORD
