Metadata-Version: 2.1
Name: python-flickr-mirroring
Version: 1.0.0
Summary: CLI for mirroring flickr photos of a specific user
Home-page: https://github.com/intek-training-jsc/flickr-mirroring-Long-Nguyen-96
Author: Long Nguyen
Author-email: long.nguyen@f4.intek.edu.com
License: UNKNOWN
Platform: UNKNOWN
Classifier: Programming Language :: Python :: 3
Classifier: License :: OSI Approved :: MIT License
Classifier: Operating System :: OS Independent
Requires-Python: >=3.6
Requires-Dist: attrs (==19.3.0)
Requires-Dist: certifi (==2020.4.5.1)
Requires-Dist: chardet (==3.0.4)
Requires-Dist: idna (==2.9)
Requires-Dist: langdetect (==1.0.8)
Requires-Dist: more-itertools (==8.2.0)
Requires-Dist: mpmath (==1.1.0)
Requires-Dist: packaging (==20.3)
Requires-Dist: pluggy (==0.13.1)
Requires-Dist: py (==1.8.1)
Requires-Dist: pyparsing (==2.4.7)
Requires-Dist: pytest (==5.4.2)
Requires-Dist: requests (==2.23.0)
Requires-Dist: six (==1.14.0)
Requires-Dist: sympy (==1.5.1)
Requires-Dist: urllib3 (==1.25.9)
Requires-Dist: wcwidth (==0.1.9)
Requires-Dist: zipp (==3.1.0)
Requires-Dist: importlib-metadata (==1.6.0) ; python_version < "3.8"
